npc/vsrc/reg.v
// module Reg #(WIDTH = 1, RESET_VAL = 0) (
//   input clk,
//   input rst,
//   input [WIDTH-1:0] din,
//   output reg [WIDTH-1:0] dout,
//   input wen
// );
//   always @(posedge clk) begin
//     if (rst) dout <= RESET_VAL;
//     else if (wen) dout <= din;
//   end
// endmodule
module ysyx_22040127_RegisterFile #(ADDR_WIDTH = 5, DATA_WIDTH = 64) (
  input clk,
  input wen,
  input [DATA_WIDTH-1:0] wdata,
  input [ADDR_WIDTH-1:0] waddr,
  input [ADDR_WIDTH-1:0] raddr1,
  input [ADDR_WIDTH-1:0] raddr2,
  output[DATA_WIDTH-1:0] rdata1,
  output[DATA_WIDTH-1:0] rdata2
);
  reg [DATA_WIDTH-1:0] rf [(1<<ADDR_WIDTH)-1:0];
  wire non_zerow;//waddr != 0
  assign non_zerow = (|waddr);
  assign rf[0] = 64'b0;
  assign rdata1 = rf[raddr1];
  assign rdata2 = rf[raddr2];
  import "DPI-C" function void set_gpr_ptr(input logic [63:0] a []);
  initial set_gpr_ptr(rf);  // rf为通用寄存器的二维数组变量

  always @(posedge clk) begin
    if (wen && (|waddr)) rf[waddr] <= wdata;
  end
endmodule

npc/vsrc/execute.v
module ysyx_22040127_execute(
  input [31:0] instruction,
  input clk,
  input rst,
  input[31:0]pc,
  input[63:0]src0,
  input[63:0]src1,
  input[63:0]imm,
  input[2:0] inst_type,
  output reg[63:0]alu_output
);
  localparam TYPE_I = 0, TYPE_U = 1, TYPE_S = 2, TYPE_J = 3, TYPE_R = 4, TYPE_B = 5;
  always @(*) begin
    case(inst_type)
      3'b000 : alu_output = src0 + src1;//I_type
      3'b001 : alu_output = instruction[5] ? src0 : src0 + {32'b0,pc}; //auipc:lui
      3'b011 : alu_output = {32'b0, pc + 4};//jal
      //32'b0,pc?
      default: alu_output = 0;
    endcase
  end
endmodule

npc/vsrc/decode.v
module ysyx_22040127_decode(
  input [31:0] instruction,
  input clk,
  input rst,
  output r_wen,
  output[4:0] rd,
  output[4:0] rs1,
  output[4:0] rs2,
  output reg[2:0] inst_type,
  output reg[63:0] imm
);
  localparam TYPE_I = 3'b000, TYPE_U = 3'b001, TYPE_S = 3'b010,
   TYPE_J = 3'b011, TYPE_R = 3'b100, TYPE_B = 3'b101, TYPE_N = 3'b110;
  assign rd  = instruction[11:7];
  assign rs1 = instruction[19:15];
  assign rs2 = instruction[24:20];
  //assign imm = {{52{instruction[31]}},instruction[31:20]};
  assign r_wen = (!(|inst_type)) || inst_type == TYPE_U || inst_type == TYPE_J;//typeI is first
  //typei,typeu writes register
  always @(*)begin
    case(inst_type)
      3'b001:imm = {{32{instruction[31]}},instruction[31:12],12'b0};
      3'b000:imm = {{52{instruction[31]}},instruction[31:20]};
      3'b011:imm = {{43{instruction[31]}},instruction[31],instruction[19:12],instruction[20],instruction[30:21],1'b0};
      3'b110:imm = {{52{instruction[31]}},instruction[31:20]};
      default:imm = 64'b0;
    endcase
  end
  // number of keys,width of key/data (output input 
  always @(*)begin
    case(instruction[6:0])
      7'b0010111:inst_type = TYPE_U;//auipc instru[5]
      7'b0110111:inst_type = TYPE_U;//lui
      7'b0011011:inst_type = TYPE_I;
      7'b1100111:inst_type = TYPE_I;//jalr
      7'b1101111:inst_type = TYPE_J;//jal
      7'b1110011:inst_type = TYPE_N;
      default:inst_type = TYPE_I;
    endcase
  end
  /*
  ysyx_22040127_MuxKey #(7, 7, 3) inst_mux (inst_type, instruction[6:0], {
    TYPE_U,7'b0010111,
    TYPE_I,7'b0011011,//addi
    TYPE_S,7'b0100011,
    TYPE_J,7'b1101111,
    TYPE_R,7'b0111011,
    TYPE_B,7'b1100011,
    TYPE_N,7'b1110011
  });
  */
endmodule

npc/vsrc/top.v
module ysyx_22040127_top(
  input clk,
  input rst,
  input  [31:0] instruction,
  output reg[31:0] pc
);
  reg [63:0] reg_wdata;
  wire [63:0] alu_output;
  wire reg_wen;
  wire[4:0]  rd;
  wire[4:0]  rs1;
  wire[4:0]  rs2;
  wire[2:0]  inst_type;
  wire[63:0] imm;//output of decode
  wire       imm_src0;//src0 is imm
  wire       imm_src1;
  wire       ebreak;
  wire[63:0] src0;
  wire[63:0] src1;
  wire[63:0] reg_data0;
  wire[63:0] reg_data1;
  wire       jalr;
  
  assign imm_src0 = (inst_type == 3'b001 || inst_type == 3'b011);//type_u,type_j
  assign imm_src1 = (inst_type == 3'b000);//type_i
  assign src0 = imm_src0 ? imm :reg_data0;
  assign src1 = imm_src1 ? imm :reg_data1;
  assign jalr = inst_type == 3'b000 && instruction[6:5] == 2'b11; 
  assign ebreak = (inst_type == 3'b110) & instruction[20]
      & !(|{instruction[31:21],instruction[19:7]});
  import "DPI-C" function void set_simtime();
  always @(*)begin
    if(jalr) reg_wdata = {32'b0, pc + 4};
    else reg_wdata = alu_output;
  end

  always @(posedge clk) begin
    if(ebreak)//TYPE_N
      set_simtime();
  end

  always @(posedge clk) begin
    if(rst == 1'b1)
      pc <= 32'h80000000;
    else if(inst_type == 3'b001 && instruction[5] || inst_type == 3'b011)//type_u:auipc,j
      pc <= pc + src0[31:0];
    else if(jalr) pc <= alu_output[31:0] & (~1);
    else pc <= pc + 4;
  end
  ysyx_22040127_decode dec(instruction, clk, rst, reg_wen, rd, rs1, rs2, inst_type, imm);
  ysyx_22040127_execute exe(instruction, clk, rst, pc, src0, src1, imm, inst_type, alu_output);
  ysyx_22040127_RegisterFile #(5, 64) regs(clk, reg_wen, reg_wdata, rd, rs1, rs2, reg_data0, reg_data1);//wb
  //Reg #(4, 4'b0) i1 (clk, rst, in, out, in[0]);
endmodule

npc/build/obj_dir/wave.vcd
$version Generated by VerilatedVcd $end
$date Mon Mar 14 19:13:10 2022 $end
$timescale 1ps $end

 $scope module TOP $end
  $var wire  1 n clk $end
  $var wire 32 p instruction [31:0] $end
  $var wire 32 q pc [31:0] $end
  $var wire  1 o rst $end
  $scope module ysyx_22040127_top $end
   $var wire 64 c alu_output [63:0] $end
   $var wire  1 n clk $end
   $var wire  1 w ebreak $end
   $var wire 64 g imm [63:0] $end
   $var wire  1 i imm_src0 $end
   $var wire  1 j imm_src1 $end
   $var wire  3 f inst_type [2:0] $end
   $var wire 32 p instruction [31:0] $end
   $var wire  1 m jalr $end
   $var wire 32 q pc [31:0] $end
   $var wire  5 t rd [4:0] $end
   $var wire 64 z reg_data0 [63:0] $end
   $var wire 64 | reg_data1 [63:0] $end
   $var wire 64 r reg_wdata [63:0] $end
   $var wire  1 e reg_wen $end
   $var wire  5 u rs1 [4:0] $end
   $var wire  5 v rs2 [4:0] $end
   $var wire  1 o rst $end
   $var wire 64 k src0 [63:0] $end
   $var wire 64 x src1 [63:0] $end
   $scope module dec $end
    $var wire  3 &! TYPE_B [2:0] $end
    $var wire  3 !! TYPE_I [2:0] $end
    $var wire  3 $! TYPE_J [2:0] $end
    $var wire  3 '! TYPE_N [2:0] $end
    $var wire  3 %! TYPE_R [2:0] $end
    $var wire  3 #! TYPE_S [2:0] $end
    $var wire  3 "! TYPE_U [2:0] $end
    $var wire  1 n clk $end
    $var wire 64 g imm [63:0] $end
    $var wire  3 f inst_type [2:0] $end
    $var wire 32 p instruction [31:0] $end
    $var wire  1 e r_wen $end
    $var wire  5 t rd [4:0] $end
    $var wire  5 u rs1 [4:0] $end
    $var wire  5 v rs2 [4:0] $end
    $var wire  1 o rst $end
   $upscope $end
   $scope module exe $end
    $var wire 32 -! TYPE_B [31:0] $end
    $var wire 32 (! TYPE_I [31:0] $end
    $var wire 32 +! TYPE_J [31:0] $end
    $var wire 32 ,! TYPE_R [31:0] $end
    $var wire 32 *! TYPE_S [31:0] $end
    $var wire 32 )! TYPE_U [31:0] $end
    $var wire 64 c alu_output [63:0] $end
    $var wire  1 n clk $end
    $var wire 64 g imm [63:0] $end
    $var wire  3 f inst_type [2:0] $end
    $var wire 32 p instruction [31:0] $end
    $var wire 32 q pc [31:0] $end
    $var wire  1 o rst $end
    $var wire 64 k src0 [63:0] $end
    $var wire 64 x src1 [63:0] $end
   $upscope $end
   $scope module regs $end
    $var wire 32 -! ADDR_WIDTH [31:0] $end
    $var wire 32 .! DATA_WIDTH [31:0] $end
    $var wire  1 n clk $end
    $var wire  1 ~ non_zerow $end
    $var wire  5 u raddr1 [4:0] $end
    $var wire  5 v raddr2 [4:0] $end
    $var wire 64 z rdata1 [63:0] $end
    $var wire 64 | rdata2 [63:0] $end
    $var wire 64 # rf[0] [63:0] $end
    $var wire 64 7 rf[10] [63:0] $end
    $var wire 64 9 rf[11] [63:0] $end
    $var wire 64 ; rf[12] [63:0] $end
    $var wire 64 = rf[13] [63:0] $end
    $var wire 64 ? rf[14] [63:0] $end
    $var wire 64 A rf[15] [63:0] $end
    $var wire 64 C rf[16] [63:0] $end
    $var wire 64 E rf[17] [63:0] $end
    $var wire 64 G rf[18] [63:0] $end
    $var wire 64 I rf[19] [63:0] $end
    $var wire 64 % rf[1] [63:0] $end
    $var wire 64 K rf[20] [63:0] $end
    $var wire 64 M rf[21] [63:0] $end
    $var wire 64 O rf[22] [63:0] $end
    $var wire 64 Q rf[23] [63:0] $end
    $var wire 64 S rf[24] [63:0] $end
    $var wire 64 U rf[25] [63:0] $end
    $var wire 64 W rf[26] [63:0] $end
    $var wire 64 Y rf[27] [63:0] $end
    $var wire 64 [ rf[28] [63:0] $end
    $var wire 64 ] rf[29] [63:0] $end
    $var wire 64 ' rf[2] [63:0] $end
    $var wire 64 _ rf[30] [63:0] $end
    $var wire 64 a rf[31] [63:0] $end
    $var wire 64 ) rf[3] [63:0] $end
    $var wire 64 + rf[4] [63:0] $end
    $var wire 64 - rf[5] [63:0] $end
    $var wire 64 / rf[6] [63:0] $end
    $var wire 64 1 rf[7] [63:0] $end
    $var wire 64 3 rf[8] [63:0] $end
    $var wire 64 5 rf[9] [63:0] $end
    $var wire  5 t waddr [4:0] $end
    $var wire 64 r wdata [63:0] $end
    $var wire  1 e wen $end
   $upscope $end
  $upscope $end
 $upscope $end
$enddefinitions $end


#1
b0000000000000000000000000000000000000000000000000000000000000000 #
b0000000000000000000000000000000000000000000000000000000000000000 %
b0000000000000000000000000000000000000000000000000000000000000000 '
b0000000000000000000000000000000000000000000000000000000000000000 )
b0000000000000000000000000000000000000000000000000000000000000000 +
b0000000000000000000000000000000000000000000000000000000000000000 -
b0000000000000000000000000000000000000000000000000000000000000000 /
b0000000000000000000000000000000000000000000000000000000000000000 1
b0000000000000000000000000000000000000000000000000000000000000000 3
b0000000000000000000000000000000000000000000000000000000000000000 5
b0000000000000000000000000000000000000000000000000000000000000000 7
b0000000000000000000000000000000000000000000000000000000000000000 9
b0000000000000000000000000000000000000000000000000000000000000000 ;
b0000000000000000000000000000000000000000000000000000000000000000 =
b0000000000000000000000000000000000000000000000000000000000000000 ?
b0000000000000000000000000000000000000000000000000000000000000000 A
b0000000000000000000000000000000000000000000000000000000000000000 C
b0000000000000000000000000000000000000000000000000000000000000000 E
b0000000000000000000000000000000000000000000000000000000000000000 G
b0000000000000000000000000000000000000000000000000000000000000000 I
b0000000000000000000000000000000000000000000000000000000000000000 K
b0000000000000000000000000000000000000000000000000000000000000000 M
b0000000000000000000000000000000000000000000000000000000000000000 O
b0000000000000000000000000000000000000000000000000000000000000000 Q
b0000000000000000000000000000000000000000000000000000000000000000 S
b0000000000000000000000000000000000000000000000000000000000000000 U
b0000000000000000000000000000000000000000000000000000000000000000 W
b0000000000000000000000000000000000000000000000000000000000000000 Y
b0000000000000000000000000000000000000000000000000000000000000000 [
b0000000000000000000000000000000000000000000000000000000000000000 ]
b0000000000000000000000000000000000000000000000000000000000000000 _
b0000000000000000000000000000000000000000000000000000000000000000 a
b0000000000000000000000000000000000000000000000000000000000000000 c
1e
b000 f
b0000000000000000000000000000000000000000000000000000000000000000 g
0i
1j
b0000000000000000000000000000000000000000000000000000000000000000 k
0m
1n
1o
b00000000000000000000000000000000 p
b00000000000000000000000000000000 q
b0000000000000000000000000000000000000000000000000000000000000000 r
b00000 t
b00000 u
b00000 v
0w
b0000000000000000000000000000000000000000000000000000000000000000 x
b0000000000000000000000000000000000000000000000000000000000000000 z
b0000000000000000000000000000000000000000000000000000000000000000 |
0~
b000 !!
b001 "!
b010 #!
b011 $!
b100 %!
b101 &!
b110 '!
b00000000000000000000000000000000 (!
b00000000000000000000000000000001 )!
b00000000000000000000000000000010 *!
b00000000000000000000000000000011 +!
b00000000000000000000000000000100 ,!
b00000000000000000000000000000101 -!
b00000000000000000000000001000000 .!
#2
0n
#3
1n
b10000000000000000000000000000000 q
#4
0n
#5
1n
#6
0n
#7
1n
#8
0n
#9
1n
#10
0n
#11
1n
#12
0n
0o
b00000000000000000000010000010011 p
b01000 t
1~
#13
1n
b10000000000000000000000000000100 q
#14
b0000000000000000000000000000000010000000000000001001000000000100 c
b001 f
b0000000000000000000000000000000000000000000000001001000000000000 g
1i
0j
b0000000000000000000000000000000000000000000000001001000000000000 k
0n
b00000000000000001001000100010111 p
b0000000000000000000000000000000010000000000000001001000000000100 r
b00010 t
b00001 u
#15
b0000000000000000000000000000000010000000000000001001000000000100 '
b0000000000000000000000000000000010000000000000001001000000001000 c
1n
b10000000000000000000000000001000 q
b0000000000000000000000000000000010000000000000001001000000001000 r
#16
b0000000000000000000000000000000010000000000000001001000000000000 c
b000 f
b1111111111111111111111111111111111111111111111111111111111111100 g
0i
1j
b0000000000000000000000000000000010000000000000001001000000000100 k
0n
b11111111110000010000000100010011 p
b0000000000000000000000000000000010000000000000001001000000000000 r
b00010 u
b11100 v
b1111111111111111111111111111111111111111111111111111111111111100 x
b0000000000000000000000000000000010000000000000001001000000000100 z
#17
b0000000000000000000000000000000010000000000000001001000000000000 '
b0000000000000000000000000000000010000000000000001000111111111100 c
b0000000000000000000000000000000010000000000000001001000000000000 k
1n
b10000000000000000000000000001100 q
b0000000000000000000000000000000010000000000000001000111111111100 r
b0000000000000000000000000000000010000000000000001001000000000000 z
#18
b0000000000000000000000000000000010000000000000000000000000010000 c
b011 f
b0000000000000000000000000000000000000000000000000000000000001100 g
1i
0j
b0000000000000000000000000000000000000000000000000000000000001100 k
0n
b00000000110000000000000011101111 p
b0000000000000000000000000000000010000000000000000000000000010000 r
b00001 t
b00000 u
b01100 v
b0000000000000000000000000000000000000000000000000000000000000000 x
b0000000000000000000000000000000000000000000000000000000000000000 z
#19
b0000000000000000000000000000000010000000000000000000000000010000 %
b0000000000000000000000000000000010000000000000000000000000011100 c
1n
b10000000000000000000000000011000 q
b0000000000000000000000000000000010000000000000000000000000011100 r
#20
b0000000000000000000000000000000010000000000000001000111111110000 c
b000 f
b1111111111111111111111111111111111111111111111111111111111110000 g
0i
1j
b0000000000000000000000000000000010000000000000001001000000000000 k
0n
b11111111000000010000000100010011 p
b0000000000000000000000000000000010000000000000001000111111110000 r
b00010 t
b00010 u
b10000 v
b1111111111111111111111111111111111111111111111111111111111110000 x
b0000000000000000000000000000000010000000000000001001000000000000 z
#21
b0000000000000000000000000000000010000000000000001000111111110000 '
b0000000000000000000000000000000010000000000000001000111111100000 c
b0000000000000000000000000000000010000000000000001000111111110000 k
1n
b10000000000000000000000000011100 q
b0000000000000000000000000000000010000000000000001000111111100000 r
b0000000000000000000000000000000010000000000000001000111111110000 z
#22
b0000000000000000000000000000000010000000000000000000000000011100 c
b001 f
b0000000000000000000000000000000000000000000000000000000000000000 g
1i
0j
b0000000000000000000000000000000000000000000000000000000000000000 k
0n
b00000000000000000000010100010111 p
b0000000000000000000000000000000010000000000000000000000000011100 r
b01010 t
b00000 u
b00000 v
b0000000000000000000000000000000000000000000000000000000000000000 x
b0000000000000000000000000000000000000000000000000000000000000000 z
#23
b0000000000000000000000000000000010000000000000000000000000011100 7
b0000000000000000000000000000000010000000000000000000000000100000 c
1n
b10000000000000000000000000100000 q
b0000000000000000000000000000000010000000000000000000000000100000 r
#24
b0000000000000000000000000000000010000000000000000000000000110000 c
b000 f
b0000000000000000000000000000000000000000000000000000000000010100 g
0i
1j
b0000000000000000000000000000000010000000000000000000000000011100 k
0n
b00000001010001010000010100010011 p
b0000000000000000000000000000000010000000000000000000000000110000 r
b01010 u
b10100 v
b0000000000000000000000000000000000000000000000000000000000010100 x
b0000000000000000000000000000000010000000000000000000000000011100 z
#25
b0000000000000000000000000000000010000000000000000000000000110000 7
b0000000000000000000000000000000010000000000000000000000001000100 c
b0000000000000000000000000000000010000000000000000000000000110000 k
1n
b10000000000000000000000000100100 q
b0000000000000000000000000000000010000000000000000000000001000100 r
b0000000000000000000000000000000010000000000000000000000000110000 z
#26
b0000000000000000000000000000000010000000000000001000111111110001 c
b0000000000000000000000000000000000000000000000000000000000000001 g
b0000000000000000000000000000000010000000000000001000111111110000 k
0n
b00000000000100010011010000100011 p
b0000000000000000000000000000000010000000000000001000111111110001 r
b01000 t
b00010 u
b00001 v
b0000000000000000000000000000000000000000000000000000000000000001 x
b0000000000000000000000000000000010000000000000001000111111110000 z
b0000000000000000000000000000000010000000000000000000000000010000 |
#27
b0000000000000000000000000000000010000000000000001000111111110001 3
1n
b10000000000000000000000000101000 q
#28
b0000000000000000000000000000000010000000000000000000000000101100 c
b011 f
b1111111111111111111111111111111111111111111111111111111111101000 g
1i
0j
b1111111111111111111111111111111111111111111111111111111111101000 k
0n
b11111110100111111111000011101111 p
b0000000000000000000000000000000010000000000000000000000000101100 r
b00001 t
b11111 u
b01001 v
b0000000000000000000000000000000000000000000000000000000000000000 x
b0000000000000000000000000000000000000000000000000000000000000000 z
b0000000000000000000000000000000000000000000000000000000000000000 |
#29
b0000000000000000000000000000000010000000000000000000000000101100 %
b0000000000000000000000000000000010000000000000000000000000010100 c
1n
b10000000000000000000000000010000 q
b0000000000000000000000000000000010000000000000000000000000010100 r
#30
b0000000000000000000000000000000000000000000000000000000000000000 c
b000 f
b0000000000000000000000000000000000000000000000000000000000000000 g
0i
1j
b0000000000000000000000000000000000000000000000000000000000000000 k
0n
b00000000000000000000010100010011 p
b0000000000000000000000000000000000000000000000000000000000000000 r
b01010 t
b00000 u
b00000 v
#31
b0000000000000000000000000000000000000000000000000000000000000000 7
1n
b10000000000000000000000000010100 q
#32
b0000000000000000000000000000000010000000000000000000000000101100 c
b0000000000000000000000000000000010000000000000000000000000101100 k
1m
0n
b00000000000000001000000001100111 p
b0000000000000000000000000000000010000000000000000000000000011000 r
b00000 t
b00001 u
b0000000000000000000000000000000010000000000000000000000000101100 z
0~
#33
b0000000000000000000000000000000010000000000000000000000000011000 #
1n
b10000000000000000000000000101100 q
b0000000000000000000000000000000010000000000000000000000000110000 r
b0000000000000000000000000000000010000000000000000000000000011000 |
#34
b0000000000000000000000000000000010000000000000000000000000110000 c
b011 f
1i
0j
b0000000000000000000000000000000000000000000000000000000000000000 k
0m
0n
b00000000000000000000000001101111 p
b00000 u
b0000000000000000000000000000000010000000000000000000000000011000 x
b0000000000000000000000000000000010000000000000000000000000011000 z
#35
b0000000000000000000000000000000010000000000000000000000000110000 #
1n
b0000000000000000000000000000000010000000000000000000000000110000 x
b0000000000000000000000000000000010000000000000000000000000110000 z
b0000000000000000000000000000000010000000000000000000000000110000 |
